MANIFEST.in
README.md
setup.cfg
setup.py
Asset_Allocation.egg-info/PKG-INFO
Asset_Allocation.egg-info/SOURCES.txt
Asset_Allocation.egg-info/dependency_links.txt
Asset_Allocation.egg-info/entry_points.txt
Asset_Allocation.egg-info/requires.txt
Asset_Allocation.egg-info/top_level.txt
asset_allocation/__init__.py
asset_allocation/app.py
asset_allocation/assetclass_cli.py
asset_allocation/cli.py
asset_allocation/config.py
asset_allocation/config_cli.py
asset_allocation/currency.py
asset_allocation/dal.py
asset_allocation/formatters.py
asset_allocation/loader.py
asset_allocation/maps.py
asset_allocation/model.py
asset_allocation/stocklink_cli.py
asset_allocation/stocks.py
asset_allocation/view_model.py
asset_allocation/templates/asset_allocation.db
asset_allocation/templates/asset_allocation.ini