Metadata-Version: 1.2
Name: Asset-Allocation
Version: 1.1.1
Summary: Asset Allocation project
Home-page: https://github.com/MisterY/Asset-Allocation
Author: Alen Siljak
Author-email: alen.siljak@gmx.com
License: GPL version 3
Keywords: personal finance asset allocation
Platform: UNKNOWN
Classifier: Development Status :: 4 - Beta
Classifier: Intended Audience :: Developers
Classifier: License :: OSI Approved :: GNU General Public License v3 (GPLv3)
Classifier: Programming Language :: Python :: 3
Classifier: Programming Language :: Python :: 3.4
Classifier: Programming Language :: Python :: 3.5
Classifier: Programming Language :: Python :: 3.6
Requires-Python: >=3.0
